setup.py
django_jquery_lightbox.egg-info/PKG-INFO
django_jquery_lightbox.egg-info/SOURCES.txt
django_jquery_lightbox.egg-info/dependency_links.txt
django_jquery_lightbox.egg-info/requires.txt
django_jquery_lightbox.egg-info/top_level.txt
jquery_lightbox/__init__.py
jquery_lightbox/models.py
jquery_lightbox/static/css/lightbox.css
jquery_lightbox/static/img/close.png
jquery_lightbox/static/img/loading.gif
jquery_lightbox/static/img/next.png
jquery_lightbox/static/img/prev.png
jquery_lightbox/static/js/lightbox.js