Metadata-Version: 1.1
Name: django-jquery-lightbox
Version: 2.6
Summary: Django package for Lightbox: a small javascript library used to overlay images on top of the current page.
Home-page: https://github.com/mikebryant/django-jquery-lightbox
Author: Mike Bryant
Author-email: mike@mikebryant.me.uk
License: Creative Commons Attribution 2.5 License
Keywords: django,jquery,lightbox,staticfiles,overlay,image
Platform: any
Classifier: Development Status :: 5 - Production/Stable
Classifier: Environment :: Web Environment
Classifier: Framework :: Django
Classifier: Intended Audience :: Developers
Classifier: Natural Language :: English
Classifier: Operating System :: OS Independent
Classifier: Programming Language :: Python
Classifier: Topic :: Utilities
